MANIFEST.in
requirements.txt
setup.py
test-requirements.txt
version.txt
cloudshell/__init__.py
cloudshell/networking/__init__.py
cloudshell/networking/odl/__init__.py
cloudshell/networking/odl/helium/__init__.py
cloudshell/networking/odl/helium/odl_helium_configuration.py
cloudshell_sdn_odl_lithium.egg-info/PKG-INFO
cloudshell_sdn_odl_lithium.egg-info/SOURCES.txt
cloudshell_sdn_odl_lithium.egg-info/dependency_links.txt
cloudshell_sdn_odl_lithium.egg-info/requires.txt
cloudshell_sdn_odl_lithium.egg-info/top_level.txt